src/__about__.py
src/__init__.py
src/geopolygonize.py
src/geopolygonizer.py
src/blobifier/blobifier.py
src/blobifier/blobifier.test.ipynb
src/segmenter/README.md
src/segmenter/__init__.py
src/segmenter/area.py
src/segmenter/boundary.py
src/segmenter/boundary_cutter.py
src/segmenter/clean_polygon.py
src/segmenter/cutpoints_computer.py
src/segmenter/fix_polygon.py
src/segmenter/fix_polygon.test.ipynb
src/segmenter/intersections_computer.py
src/segmenter/mapping_computer.py
src/segmenter/orientation.py
src/segmenter/piece.py
src/segmenter/positioned_point.py
src/segmenter/references_computer.py
src/segmenter/segment.py
src/segmenter/segmenter.py
src/utils/__init__.py
src/utils/clean_exit.py
src/utils/smoothing.py
src/utils/tiler.py
src/utils/unifier.py
geopolygonize-0.2.2.dist-info/METADATA
geopolygonize-0.2.2.dist-info/WHEEL
geopolygonize-0.2.2.dist-info/entry_points.txt
geopolygonize-0.2.2.dist-info/RECORD
