Metadata-Version: 2.1
Name: geopolygonize
Version: 0.2.2
Summary: Convert geographic rasters into simplified polygons
Project-URL: Documentation, https://github.com/rainflame/geopolygonize#readme
Project-URL: Issues, https://github.com/rainflame/geopolygonize/issues
Project-URL: Source, https://github.com/rainflame/geopolygonize
Author-email: Sydney Zheng <slzheng@alumni.cmu.edu>, Christian Broms <christian@rainflame.com>
License-Expression: MIT
Classifier: Development Status :: 4 - Beta
Classifier: Programming Language :: Python
Classifier: Programming Language :: Python :: 3.9
Classifier: Programming Language :: Python :: 3.10
Classifier: Programming Language :: Python :: 3.11
Classifier: Topic :: Multimedia :: Graphics
Classifier: Topic :: Multimedia :: Graphics :: Graphics Conversion
Classifier: Topic :: Scientific/Engineering :: GIS
Classifier: Topic :: Scientific/Engineering :: Visualization
Requires-Python: >=3.10
Requires-Dist: geopandas>=0.14.1
Requires-Dist: numpy>=1.26.2
Requires-Dist: rasterio>=1.0.0
Requires-Dist: rtree>=1.1.0
Requires-Dist: scipy>=1.11.0
Requires-Dist: shapely>=2.0.0
Requires-Dist: sortedcontainers>=2.4.0
Requires-Dist: tqdm>=4.66.1
